imposter/__init__.py
imposter/helpers.py
imposter/logging.ini
imposter/routes.py
imposter/service.py
imposter-0.0.13.dist-info/DESCRIPTION.rst
imposter-0.0.13.dist-info/METADATA
imposter-0.0.13.dist-info/RECORD
imposter-0.0.13.dist-info/WHEEL
imposter-0.0.13.dist-info/entry_points.txt
imposter-0.0.13.dist-info/metadata.json
imposter-0.0.13.dist-info/top_level.txt
