Metadata-Version: 2.0
Name: imposter
Version: 0.0.13
Summary: AWS EC2 Metadata Imposter Service
Home-page: https://github.com/jamesboehmer/imposter
Author: James Boehmer
Author-email: james.boehmer@gmail.com
License: UNKNOWN
Platform: UNKNOWN
Requires-Dist: Flask (==0.12)
Requires-Dist: boto (==2.45.0)
Requires-Dist: gunicorn (==19.6.0)
Requires-Dist: requests (==2.13.0)
